#ifndef OPCODES_H
#define OPCODES_H

namespace toyc {
  
const int _NOP                       = 0;
const int _ACONST_NULL               = 1;
const int _ICONST_M1                 = 2;
const int _ICONST_0                  = 3;
const int _ICONST_1                  = 4;
const int _ICONST_2                  = 5;
const int _ICONST_3                  = 6;
const int _ICONST_4                  = 7;
const int _ICONST_5                  = 8;
const int _LCONST_0                  = 9;
const int _LCONST_1                  = 10;
const int _FCONST_0                  = 11;
const int _FCONST_1                  = 12;
const int _FCONST_2                  = 13;
const int _DCONST_0                  = 14;
const int _DCONST_1                  = 15;
const int _BIPUSH                    = 16;
const int _SIPUSH                    = 17;
const int _LDC                       = 18;
const int _LDC_W                     = 19;
const int _LDC2_W                    = 20;
const int _ILOAD                     = 21;
const int _LLOAD                     = 22;
const int _FLOAD                     = 23;
const int _DLOAD                     = 24;
const int _ALOAD                     = 25;
const int _ILOAD_0                   = 26;
const int _ILOAD_1                   = 27;
const int _ILOAD_2                   = 28;
const int _ILOAD_3                   = 29;
const int _LLOAD_0                   = 30;
const int _LLOAD_1                   = 31;
const int _LLOAD_2                   = 32;
const int _LLOAD_3                   = 33;
const int _FLOAD_0                   = 34;
const int _FLOAD_1                   = 35;
const int _FLOAD_2                   = 36;
const int _FLOAD_3                   = 37;
const int _DLOAD_0                   = 38;
const int _DLOAD_1                   = 39;
const int _DLOAD_2                   = 40;
const int _DLOAD_3                   = 41;
const int _ALOAD_0                   = 42;
const int _ALOAD_1                   = 43;
const int _ALOAD_2                   = 44;
const int _ALOAD_3                   = 45;
const int _IALOAD                    = 46;
const int _LALOAD                    = 47;
const int _FALOAD                    = 48;
const int _DALOAD                    = 49;
const int _AALOAD                    = 50;
const int _BALOAD                    = 51;
const int _CALOAD                    = 52;
const int _SALOAD                    = 53;
const int _ISTORE                    = 54;
const int _LSTORE                    = 55;
const int _FSTORE                    = 56;
const int _DSTORE                    = 57;
const int _ASTORE                    = 58;
const int _ISTORE_0                  = 59;
const int _ISTORE_1                  = 60;
const int _ISTORE_2                  = 61;
const int _ISTORE_3                  = 62;
const int _LSTORE_0                  = 63;
const int _LSTORE_1                  = 64;
const int _LSTORE_2                  = 65;
const int _LSTORE_3                  = 66;
const int _FSTORE_0                  = 67;
const int _FSTORE_1                  = 68;
const int _FSTORE_2                  = 69;
const int _FSTORE_3                  = 70;
const int _DSTORE_0                  = 71;
const int _DSTORE_1                  = 72;
const int _DSTORE_2                  = 73;
const int _DSTORE_3                  = 74;
const int _ASTORE_0                  = 75;
const int _ASTORE_1                  = 76;
const int _ASTORE_2                  = 77;
const int _ASTORE_3                  = 78;
const int _IASTORE                   = 79;
const int _LASTORE                   = 80;
const int _FASTORE                   = 81;
const int _DASTORE                   = 82;
const int _AASTORE                   = 83;
const int _BASTORE                   = 84;
const int _CASTORE                   = 85;
const int _SASTORE                   = 86;
const int _POP                       = 87;
const int _POP2                      = 88;
const int _DUP                       = 89;
const int _DUP_X1                    = 90;
const int _DUP_X2                    = 91;
const int _DUP2                      = 92;
const int _DUP2_X1                   = 93;
const int _DUP2_X2                   = 94;
const int _SWAP                      = 95;
const int _IADD                      = 96;
const int _LADD                      = 97;
const int _FADD                      = 98;
const int _DADD                      = 99;
const int _ISUB                      = 100;
const int _LSUB                      = 101;
const int _FSUB                      = 102;
const int _DSUB                      = 103;
const int _IMUL                      = 104;
const int _LMUL                      = 105;
const int _FMUL                      = 106;
const int _DMUL                      = 107;
const int _IDIV                      = 108;
const int _LDIV                      = 109;
const int _FDIV                      = 110;
const int _DDIV                      = 111;
const int _IREM                      = 112;
const int _LREM                      = 113;
const int _FREM                      = 114;
const int _DREM                      = 115;
const int _INEG                      = 116;
const int _LNEG                      = 117;
const int _FNEG                      = 118;
const int _DNEG                      = 119;
const int _ISHL                      = 120;
const int _LSHL                      = 121;
const int _ISHR                      = 122;
const int _LSHR                      = 123;
const int _IUSHR                     = 124;
const int _LUSHR                     = 125;
const int _IAND                      = 126;
const int _LAND                      = 127;
const int _IOR                       = 128;
const int _LOR                       = 129;
const int _IXOR                      = 130;
const int _LXOR                      = 131;
const int _IINC                      = 132;
const int _I2L                       = 133;
const int _I2F                       = 134;
const int _I2D                       = 135;
const int _L2I                       = 136;
const int _L2F                       = 137;
const int _L2D                       = 138;
const int _F2I                       = 139;
const int _F2L                       = 140;
const int _F2D                       = 141;
const int _D2I                       = 142;
const int _D2L                       = 143;
const int _D2F                       = 144;
const int _I2B                       = 145;
const int _I2C                       = 146;
const int _I2S                       = 147;
const int _LCMP                      = 148;
const int _FCMPL                     = 149;
const int _FCMPG                     = 150;
const int _DCMPL                     = 151;
const int _DCMPG                     = 152;
const int _IFEQ                      = 153;
const int _IFNE                      = 154;
const int _IFLT                      = 155;
const int _IFGE                      = 156;
const int _IFGT                      = 157;
const int _IFLE                      = 158;
const int _IF_ICMPEQ                 = 159;
const int _IF_ICMPNE                 = 160;
const int _IF_ICMPLT                 = 161;
const int _IF_ICMPGE                 = 162;
const int _IF_ICMPGT                 = 163;
const int _IF_ICMPLE                 = 164;
const int _IF_ACMPEQ                 = 165;
const int _IF_ACMPNE                 = 166;
const int _GOTO                      = 167;
const int _JSR                       = 168;
const int _RET                       = 169;
const int _TABLESWITCH               = 170;
const int _LOOKUPSWITCH              = 171;
const int _IRETURN                   = 172;
const int _LRETURN                   = 173;
const int _FRETURN                   = 174;
const int _DRETURN                   = 175;
const int _ARETURN                   = 176;
const int _RETURN                    = 177;
const int _GETSTATIC                 = 178;
const int _PUTSTATIC                 = 179;
const int _GETFIELD                  = 180;
const int _PUTFIELD                  = 181;
const int _INVOKEVIRTUAL             = 182;
const int _INVOKENONVIRTUAL          = 183;
const int _INVOKESTATIC              = 184;
const int _INVOKEINTERFACE           = 185;
const int _NEW                       = 187;
const int _NEWARRAY                  = 188;
const int _ANEWARRAY                 = 189;
const int _ARRAYLENGTH               = 190;
const int _ATHROW                    = 191;
const int _CHECKCAST                 = 192;
const int _INSTANCEOF                = 193;
const int _MONITORENTER              = 194;
const int _MONITOREXIT               = 195;
const int _WIDE                      = 196;
const int _MULTIANEWARRAY            = 197;
const int _IFNULL                    = 198;
const int _IFNONNULL                 = 199;
const int _GOTO_W                    = 200;
const int _JSR_W                     = 201;
const int _BREAKPOINT                = 202;
const int _LDC_QUICK                 = 203;
const int _LDC2_QUICK                = 205;
const int _GETFIELD_QUICK            = 206;
const int _PUTFIELD_QUICK            = 207;
const int _GETFIELD2_QUICK           = 208;
const int _PUTFIELD2_QUICK           = 209;
const int _PUTSTATIC_QUICK           = 211;
const int _GETSTATIC2_QUICK          = 212;
const int _PUTSTATIC2_QUICK          = 213;
const int _INVOKEVIRTUAL_QUICK       = 214;
const int _INVOKENONVIRTUAL_QUICK    = 215;
const int _INVOKESUPER_QUICK         = 216;
const int _INVOKESTATIC_QUICK        = 217;
const int _INVOKEINTERFACE_QUICK     = 218;
const int _INVOKEVIRTUALOBJECT_QUICK = 219;
const int _NEW_QUICK                 = 221;
const int _ANEWARRAY_QUICK           = 222;
const int _MULTIANEWARRAY_QUICK      = 223;
const int _CHECKCAST_QUICK           = 224;
const int _INSTANCEOF_QUICK          = 225;
const int _INVOKEVIRTUAL_QUICK_W     = 226;
const int _GETFIELD_QUICK_W          = 227;
const int _PUTFIELD_QUICK_W          = 228;
const int _IMPDEP1                   = 254;
const int _IMPDEP2                   = 255;
 
}

#endif
